urbanlivabilityscore.py
urbanlivabilityscore-0.0.1.dist-info/LICENSE
urbanlivabilityscore-0.0.1.dist-info/METADATA
urbanlivabilityscore-0.0.1.dist-info/WHEEL
urbanlivabilityscore-0.0.1.dist-info/top_level.txt
urbanlivabilityscore-0.0.1.dist-info/RECORD
