Metadata-Version: 2.1
Name: urbanlivabilityscore
Version: 0.0.1
Summary: This package provides functions to calculate various livability scores
Home-page: https://github.com/BharatSingh314/UrbanLivabilityScore.git
Author: Bharat Singh and Vaidehi Raipat
Author-email: bharat.singh.1908@gmail.com
Classifier: Programming Language :: Python :: 3
Classifier: License :: OSI Approved :: BSD License
Classifier: Operating System :: OS Independent
License-File: LICENSE
